hawk_extension/__init__.py
hawk_extension/server.py
hawk_extension/extension/BG.jpeg
hawk_extension/extension/background.js
hawk_extension/extension/logomain.png
hawk_extension/extension/manifest.json
hawk_extension/extension/popup.css
hawk_extension/extension/popup.html
hawk_extension/extension/popup.js
hawk_extension/extension/icons/background.png
hawk_extension/extension/icons/hawk128.png
hawk_extension/extension/icons/hawk16.png
hawk_extension/extension/icons/hawk48.png
hawk_extension/extension/icons/icon128.png
hawk_extension/extension/icons/icon16.png
hawk_extension/extension/icons/icon48.png
hawk_extension/extension/model/model.json
hawk_extension/extension/model/tf.min.js
hawk_extension/extension/model/tokenizer.json
hawk_v1-1.0.3.dist-info/METADATA
hawk_v1-1.0.3.dist-info/WHEEL
hawk_v1-1.0.3.dist-info/entry_points.txt
hawk_v1-1.0.3.dist-info/top_level.txt
hawk_v1-1.0.3.dist-info/RECORD
