Metadata-Version: 2.1
Name: hawk-v1
Version: 1.0.3
Summary: H.A.W.K - High-Accuracy Wordsmithing Kernel - Chrome Extension Installer
Home-page: https://github.com/hawk-team/hawk-extension
Author: HAWK Team
Author-email: info@hawk-extension.com
Classifier: Programming Language :: Python :: 3
Classifier: License :: OSI Approved :: MIT License
Classifier: Operating System :: OS Independent
Requires-Python: >=3.7
Requires-Dist: flask >=2.0.0
Requires-Dist: waitress >=2.0.0
Requires-Dist: packaging >=21.0
